simpleregistry/__init__.py
simpleregistry/base.py
simpleregistry/exceptions.py
simpleregistry-0.2.2.dist-info/METADATA
simpleregistry-0.2.2.dist-info/WHEEL
simpleregistry-0.2.2.dist-info/licenses/LICENSE
simpleregistry-0.2.2.dist-info/RECORD
